stirrup/__init__.py
stirrup/clients/__init__.py
stirrup/clients/chat_completions_client.py
stirrup/clients/litellm_client.py
stirrup/clients/open_responses_client.py
stirrup/clients/utils.py
stirrup/constants.py
stirrup/core/__init__.py
stirrup/core/agent.py
stirrup/core/cache.py
stirrup/core/exceptions.py
stirrup/core/models.py
stirrup/prompts/__init__.py
stirrup/prompts/base_system_prompt.txt
stirrup/prompts/message_summarizer.txt
stirrup/prompts/message_summarizer_bridge.txt
stirrup/py.typed
stirrup/skills/__init__.py
stirrup/skills/skills.py
stirrup/tools/__init__.py
stirrup/tools/browser_use.py
stirrup/tools/calculator.py
stirrup/tools/code_backends/__init__.py
stirrup/tools/code_backends/base.py
stirrup/tools/code_backends/docker.py
stirrup/tools/code_backends/e2b.py
stirrup/tools/code_backends/local.py
stirrup/tools/finish.py
stirrup/tools/mcp.py
stirrup/tools/user_input.py
stirrup/tools/view_image.py
stirrup/tools/web.py
stirrup/utils/__init__.py
stirrup/utils/logging.py
stirrup/utils/text.py
stirrup-0.1.5.dist-info/WHEEL
stirrup-0.1.5.dist-info/METADATA
stirrup-0.1.5.dist-info/RECORD
