Metadata-Version: 2.3
Name: stirrup
Version: 0.1.5
Summary: The lightweight foundation for building agents
Keywords: ai,agent,llm,openai,anthropic,tools,framework
Author: Artificial Analysis, Inc.
Author-email: Artificial Analysis, Inc. <info@artificialanalysis.ai>
License: MIT License
Classifier: Development Status :: 4 - Beta
Classifier: Intended Audience :: Developers
Classifier: License :: OSI Approved :: MIT License
Classifier: Operating System :: OS Independent
Classifier: Programming Language :: Python :: 3
Classifier: Programming Language :: Python :: 3.12
Classifier: Programming Language :: Python :: 3.13
Classifier: Topic :: Scientific/Engineering :: Artificial Intelligence
Classifier: Topic :: Software Development :: Libraries :: Python Modules
Classifier: Typing :: Typed
Requires-Dist: anyio>=4.0.0
Requires-Dist: filetype>=1.0.0
Requires-Dist: httpx>=0.20.0
Requires-Dist: json-schema-to-pydantic>=0.2.0
Requires-Dist: moviepy>=2.0.0
Requires-Dist: openai>=1.0.0
Requires-Dist: pillow>=10.4.0
Requires-Dist: pydantic>=2.0.0
Requires-Dist: rich>=13.0.0
Requires-Dist: tenacity>=5.0.0
Requires-Dist: trafilatura>=1.9.0
Requires-Dist: stirrup[litellm,e2b,docker,mcp,browser] ; extra == 'all'
Requires-Dist: browser-use>=0.11.3 ; extra == 'browser'
Requires-Dist: docker>=7.0.0 ; extra == 'docker'
Requires-Dist: python-dotenv>=1.0.0 ; extra == 'docker'
Requires-Dist: e2b-code-interpreter>=2.3.0 ; extra == 'e2b'
Requires-Dist: litellm>=1.79.3 ; extra == 'litellm'
Requires-Dist: mcp>=1.9.0 ; extra == 'mcp'
Requires-Python: >=3.12
Project-URL: Homepage, https://github.com/ArtificialAnalysis/Stirrup
Project-URL: Documentation, https://stirrup.artificialanalysis.ai
Project-URL: Repository, https://github.com/ArtificialAnalysis/Stirrup
Provides-Extra: all
Provides-Extra: browser
Provides-Extra: docker
Provides-Extra: e2b
Provides-Extra: litellm
Provides-Extra: mcp
